README.md
setup.py
pycliwrapper/__init__.py
pycliwrapper.egg-info/PKG-INFO
pycliwrapper.egg-info/SOURCES.txt
pycliwrapper.egg-info/dependency_links.txt
pycliwrapper.egg-info/top_level.txt