Metadata-Version: 2.1
Name: pycliwrapper
Version: 1.0
Summary: Wrap any CLI tool to Python like syntax
Home-page: UNKNOWN
Author: Jordi Deu-Pons
License: Apache License 2.0
Keywords: cli,wrapper
Platform: UNKNOWN
Classifier: Development Status :: 5 - Production/Stable
Classifier: License :: OSI Approved :: Apache Software License
Classifier: Intended Audience :: Developers
